flm_templates/__init__.py
flm_templates/_jinja2template.py
flm_templates/templates/.DS_Store
flm_templates/templates/html/.DS_Store
flm_templates/templates/html/oldtextbook/header-embed-svg.svg
flm_templates/templates/html/oldtextbook/header-embed-svg.svg~
flm_templates/templates/html/oldtextbook/main_old_textbook.html
flm_templates/templates/html/oldtextbook/main_old_textbook.html~
flm_templates/templates/html/oldtextbook/oldtxtbkstyle.css
flm_templates/templates/html/oldtextbook/oldtxtbkstyle.css~
flm_templates/templates/html/oldtextbook/paper-bg.jpg
flm_templates/templates/html/oldtextbook.yaml
flm_templates/templates/html/oldtextbook.yaml~
flm_templates/templates/html/sunset/main.html
flm_templates/templates/html/sunset/main.html~
flm_templates/templates/html/sunset/sunsetstyle.css
flm_templates/templates/html/sunset/sunsetstyle.css~
flm_templates/templates/html/sunset.yaml
flm_templates/templates/html/sunset.yaml~
flm_templates-0.1.2.dist-info/LICENSE
flm_templates-0.1.2.dist-info/WHEEL
flm_templates-0.1.2.dist-info/METADATA
flm_templates-0.1.2.dist-info/RECORD
