Metadata-Version: 2.1
Name: flm-templates
Version: 0.1.2
Summary: Better templates for LLM output, especially for HTML
License: MIT
Author: Philippe Faist
Requires-Python: >=3.8,<4.0
Classifier: License :: OSI Approved :: MIT License
Classifier: Programming Language :: Python :: 3
Classifier: Programming Language :: Python :: 3.8
Classifier: Programming Language :: Python :: 3.9
Classifier: Programming Language :: Python :: 3.10
Classifier: Programming Language :: Python :: 3.11
Requires-Dist: Jinja2 (>=3.1.2,<4.0.0)
Requires-Dist: flm-core (>=0.3.0a10)
